woodtapper
