Metadata-Version: 2.4
Name: woodtapper
Version: 0.0.12
Summary: A Python toolbox for interpretable and explainable tree ensembles.
Author: Abdoulaye SAKHO
Author-email: Abdoulaye SAKHO <abdoulaye7020@gmail.com>, artefactory <abdoulaye.sakho@artefact.com>
License-Expression: MIT
Project-URL: Homepage, https://github.com/artefactory/woodtapper
Project-URL: Repository, https://github.com/artefactory/woodtapper
Keywords: woodtapper,interpretable ML,tree-based models,Cython
Classifier: Programming Language :: Python :: 3.11
Classifier: Programming Language :: Python :: 3.12
Classifier: Topic :: Scientific/Engineering :: Mathematics
Classifier: Topic :: Software Development
Requires-Python: <3.13,>=3.11
License-File: LICENSE
Requires-Dist: numpy>=2.3.1
Requires-Dist: pandas>=2.3.0
Requires-Dist: scikit-learn>=1.6.1
Requires-Dist: ucimlrepo>=0.0.7
Provides-Extra: dev
Requires-Dist: pytest>=8.4.2; extra == "dev"
Requires-Dist: pytest-cov>=7.0.0; extra == "dev"
Requires-Dist: pre-commit>=4.3.0; extra == "dev"
Requires-Dist: matplotlib>=3.10.0; extra == "dev"
Provides-Extra: docs
Requires-Dist: mkdocs>=1.6.1; extra == "docs"
Requires-Dist: mkdocs-material>=9.6.22; extra == "docs"
Requires-Dist: mkdocstrings-python>=1.18.2; extra == "docs"
Dynamic: author
Dynamic: license-file
